tweaktune-0.0.1a12.dist-info/METADATA
tweaktune-0.0.1a12.dist-info/WHEEL
tweaktune-0.0.1a12.dist-info/licenses/LICENSE
tweaktune/ui/__init__.py
tweaktune/ui/__pycache__/__init__.cpython-310.pyc
tweaktune/chat_templates/__init__.py
tweaktune/chat_templates/__pycache__/__init__.cpython-310.pyc
tweaktune/tools.py
tweaktune/structured.py
tweaktune/__init__.py
tweaktune/chain.py
tweaktune/__pycache__/__init__.cpython-310.pyc
tweaktune/__pycache__/datasets.cpython-310.pyc
tweaktune/__pycache__/tools.cpython-310.pyc
tweaktune/__pycache__/wrappers.cpython-310.pyc
tweaktune/__pycache__/common.cpython-310.pyc
tweaktune/__pycache__/tune.cpython-310.pyc
tweaktune/__pycache__/structured.cpython-310.pyc
tweaktune/__pycache__/chain.cpython-310.pyc
tweaktune/tune.py
tweaktune/wrappers.py
tweaktune/common.py
tweaktune/tweaktune.abi3.so
tweaktune-0.0.1a12.dist-info/RECORD
