Metadata-Version: 2.4
Name: tweaktune
Version: 0.0.1a12
Classifier: Programming Language :: Rust
Classifier: Programming Language :: Python :: Implementation :: CPython
Classifier: Programming Language :: Python :: Implementation :: PyPy
Requires-Dist: pydantic ~=2.10.6
Requires-Dist: pytest ~=8.3.5 ; extra == 'dev'
Requires-Dist: pytest-cov ~=6.1.1 ; extra == 'dev'
Requires-Dist: black ~=25.1.0 ; extra == 'dev'
Requires-Dist: isort ~=6.0.1 ; extra == 'dev'
Requires-Dist: mypy ~=1.5.0 ; extra == 'dev'
Requires-Dist: flake8 ~=7.2.0 ; extra == 'dev'
Requires-Dist: ruff ~=0.11.8 ; extra == 'dev'
Requires-Dist: pydocstyle ~=6.3.0 ; extra == 'dev'
Requires-Dist: polars ~=1.29.0 ; extra == 'dev'
Requires-Dist: connectorx ~=0.4.3 ; extra == 'db'
Requires-Dist: datasets ~=3.2.0 ; extra == 'arrow'
Requires-Dist: pyarrow ~=20.0.0 ; extra == 'arrow'
Requires-Dist: unsloth ~=2025.1.8 ; extra == 'unsloth'
Provides-Extra: dev
Provides-Extra: db
Provides-Extra: arrow
Provides-Extra: unsloth
License-File: LICENSE
Summary: A Python package for syntesize datasets for training and fine-tuning AI models.
Keywords: llm,ai,machine-learning
License: MIT OR Apache-2.0
Requires-Python: >=3.8
Project-URL: repository, https://github.com/qooba/tweaktune
